{
  "project_info": {
    "project_number": "986557774672",
    "project_id": "fir-c8bb2",
    "storage_bucket": "fir-c8bb2.firebasestorage.app"
  },
  "client": [
    {
      "client_info": {
        "mobilesdk_app_id": "1:986557774672:android:2750eff7190cd133d30a55",
        "android_client_info": {
          "package_name": "com.mobileapp"
        }
      },
      "oauth_client": [],
      "api_key": [
        {
          "current_key": "AIzaSyAPBorFZixfM-P6x1aJh255VGZnddp924Q"
        }
      ],
      "services": {
        "appinvite_service": {
          "other_platform_oauth_client": []
        }
      }
    }
  ],
  "configuration_version": "1"
}